lazip.py
lazip-0.0.5.dist-info/LICENSE
lazip-0.0.5.dist-info/WHEEL
lazip-0.0.5.dist-info/METADATA
lazip-0.0.5.dist-info/RECORD
